objectid/__init__.py
objectid/models.py
objectid/objectid.py
objectid/snowflake.py
objectid/test.py
objectid/utils.py
django_objectid-1.0.10.dist-info/LICENSE
django_objectid-1.0.10.dist-info/METADATA
django_objectid-1.0.10.dist-info/WHEEL
django_objectid-1.0.10.dist-info/top_level.txt
django_objectid-1.0.10.dist-info/RECORD
