Metadata-Version: 2.1
Name: django-objectid
Version: 1.0.10
Summary: django objectid
Home-page: https://github.com/tangdyy/django-objectid
Author: Tang dayong
Author-email: tangdyy@126.com
Classifier: Programming Language :: Python :: 3
Classifier: License :: OSI Approved :: MIT License
Classifier: Operating System :: OS Independent
Requires-Python: >=3.6
License-File: LICENSE
Requires-Dist: django >=2.2.0
